dtcontrol/bdd.py
dtcontrol/benchmark_suite.py
dtcontrol/benchmark_suite_classifier.py
dtcontrol/cli.py
dtcontrol/config.yml
dtcontrol/frontend_helper.py
dtcontrol/globals.py
dtcontrol/timeout.py
dtcontrol/util.py
dtcontrol/c_templates/multi_output.c
dtcontrol/c_templates/single_output.c
dtcontrol/dataset/csv_dataset_loader.py
dtcontrol/dataset/dataset.py
dtcontrol/dataset/dataset_loader.py
dtcontrol/dataset/multi_output_dataset.py
dtcontrol/dataset/prism_dataset_loader.py
dtcontrol/dataset/scots_dataset_loader.py
dtcontrol/dataset/single_output_dataset.py
dtcontrol/dataset/storm_dataset_loader.py
dtcontrol/dataset/uppaal_dataset_loader.py
dtcontrol/decision_tree/decision_tree.py
dtcontrol/decision_tree/max_cart_forest.py
dtcontrol/decision_tree/OC1_source/README
dtcontrol/decision_tree/OC1_source/classify.c
dtcontrol/decision_tree/OC1_source/classify_util.c
dtcontrol/decision_tree/OC1_source/compute_impurity.c
dtcontrol/decision_tree/OC1_source/display.c
dtcontrol/decision_tree/OC1_source/display.readme
dtcontrol/decision_tree/OC1_source/gendata.c
dtcontrol/decision_tree/OC1_source/gendata.readme
dtcontrol/decision_tree/OC1_source/impurity_measures.c
dtcontrol/decision_tree/OC1_source/load_data.c
dtcontrol/decision_tree/OC1_source/makefile
dtcontrol/decision_tree/OC1_source/mktree.c
dtcontrol/decision_tree/OC1_source/mktree.readme
dtcontrol/decision_tree/OC1_source/myprune.c
dtcontrol/decision_tree/OC1_source/oc1.h
dtcontrol/decision_tree/OC1_source/oc1_bkp.h
dtcontrol/decision_tree/OC1_source/perturb.c
dtcontrol/decision_tree/OC1_source/prune.c
dtcontrol/decision_tree/OC1_source/source_code.readme
dtcontrol/decision_tree/OC1_source/train_util.c
dtcontrol/decision_tree/OC1_source/tree_util.c
dtcontrol/decision_tree/OC1_source/util.c
dtcontrol/decision_tree/determinization/determinizer.py
dtcontrol/decision_tree/determinization/label_powerset_determinizer.py
dtcontrol/decision_tree/determinization/max_freq_determinizer.py
dtcontrol-2.1.15.dist-info/LICENSE
dtcontrol-2.1.15.dist-info/METADATA
dtcontrol-2.1.15.dist-info/WHEEL
dtcontrol-2.1.15.dist-info/entry_points.txt
dtcontrol-2.1.15.dist-info/top_level.txt
dtcontrol-2.1.15.dist-info/RECORD
