Metadata-Version: 2.1
Name: dtcontrol
Version: 2.1.15
Summary: A small tool which can convert automatically synthesised formally verified controllers into concise decision trees.
Home-page: https://dtcontrol.model.in.tum.de/
Author: Christoph Weinhuber
Author-email: christoph.weinhuber@tum.de
License: MIT
Platform: UNKNOWN
Classifier: Programming Language :: Python :: 3.8
Classifier: Programming Language :: Python :: 3.9
Classifier: License :: OSI Approved :: MIT License
Requires-Python: >=3.8
Requires-Dist: Flask (>=2.0.3)
Requires-Dist: dd (>=0.5.7)
Requires-Dist: pandas (>=1.4.1)
Requires-Dist: ruamel.yaml (>=0.17.21)
Requires-Dist: scikit-learn (>=1.0.2)
Requires-Dist: sympy (>=1.9)
Requires-Dist: tabulate (>=0.8.9)
Requires-Dist: tqdm (>=4.62.3)
